business_metrics.py
cringeHW1-0.0.1.dist-info/METADATA
cringeHW1-0.0.1.dist-info/WHEEL
cringeHW1-0.0.1.dist-info/entry_points.txt
cringeHW1-0.0.1.dist-info/top_level.txt
cringeHW1-0.0.1.dist-info/RECORD
